opencpaas/__init__.py
opencpaas/cpaas.py
opencpaas/exceptions.py
opencpaas-0.0.1.dist-info/LICENSE
opencpaas-0.0.1.dist-info/METADATA
opencpaas-0.0.1.dist-info/WHEEL
opencpaas-0.0.1.dist-info/top_level.txt
opencpaas-0.0.1.dist-info/RECORD
