Metadata-Version: 2.1
Name: opencpaas
Version: 0.0.1
Summary: An SDK that allows flexibility between CPaaS providers.
Home-page: https://github.com/Bandwidth/OpenCpaas/
Author: Perri Smith
Author-email: dx@bandwidth.com
License: UNKNOWN
Platform: UNKNOWN
Classifier: Programming Language :: Python :: 3
Classifier: License :: OSI Approved :: MIT License
Classifier: Operating System :: OS Independent
